gakp_pylib-0.9.3.dist-info/DESCRIPTION.rst
gakp_pylib-0.9.3.dist-info/LICENSE.txt
gakp_pylib-0.9.3.dist-info/METADATA
gakp_pylib-0.9.3.dist-info/RECORD
gakp_pylib-0.9.3.dist-info/WHEEL
gakp_pylib-0.9.3.dist-info/metadata.json
gakp_pylib-0.9.3.dist-info/top_level.txt
pylib/__init__.py
pylib/falcon/__init__.py
pylib/falcon/api.py
pylib/falcon/collection.py
pylib/falcon/entity.py
pylib/falcon/hooks.py
pylib/falcon/middleware.py
pylib/falcon/search.py
pylib/lib/__init__.py
pylib/marshmallow/__init__.py
pylib/marshmallow/fields.py
pylib/marshmallow/schema.py
pylib/marshmallow/serialize.py
pylib/marshmallow/validators.py
pylib/security/__init__.py
pylib/security/password.py
pylib/security/tokens.py
tests/__init__.py
tests/dictutils.py
tests/falcon.py
tests/functions.py
tests/search.py
tests/test_falcon.py
tests/validator.py
webcut/__init__.py
webcut/falcon/__init__.py
webcut/falcon/api.py
webcut/falcon/collection.py
webcut/falcon/entity.py
webcut/falcon/hooks.py
webcut/falcon/middleware.py
webcut/falcon/search.py
webcut/lib/__init__.py
webcut/marshmallow/__init__.py
webcut/marshmallow/fields.py
webcut/marshmallow/schema.py
webcut/marshmallow/serialize.py
webcut/marshmallow/validators.py
webcut/security/__init__.py
webcut/security/password.py
webcut/security/tokens.py
