Metadata-Version: 2.0
Name: gakp-pylib
Version: 0.9.3
Summary: UNKNOWN
Home-page: https://gitlab.com/gakp/pylib.git
Author: gatekeeper
Author-email: arewa.olakunle@gmail.com
License: UNKNOWN
Platform: any
Requires-Dist: PyJWT (==1.4.2)
Requires-Dist: falcon (==0.3.0)
Requires-Dist: gakp-pyfunk (==0.4.0)
Requires-Dist: marshmallow (==2.7.1)
Requires-Dist: pymongo (==3.2.2)
Requires-Dist: pytz (==2016.4)
